<?xml version="1.0" encoding="UTF-8" standalone="yes"?>
<ModMetaData>
    <packageId>wishRobber.moadvancedmining</packageId>
    <name>Medieval Overhaul - Advanced Mining</name>
    <author>wishRobber</author>
    <description>Integrate Mines 2.0 into your Medieval Overhaul mine shaft. This ties Mines 2.0's deep-mining recipes and research to Medieval Overhaul's mine shaft (renamed "Advanced Mining") and hides the redundant Mines 2.0 building, for one clean medieval mining system.</description>
    <supportedVersions>
        <li>1.6</li>
    </supportedVersions>
    <modDependencies>
        <li>
            <packageId>Cain.Mineshaft</packageId>
            <displayName>Mines 2.0</displayName>
            <steamWorkshopUrl>steam://url/CommunityFilePage/2503894706</steamWorkshopUrl>
        </li>
        <li>
            <packageId>DankPyon.Medieval.Overhaul</packageId>
            <displayName>Medieval Overhaul</displayName>
            <steamWorkshopUrl>steam://url/CommunityFilePage/3219596926</steamWorkshopUrl>
        </li>
    </modDependencies>
    <loadAfter>
        <li>Cain.Mineshaft</li>
        <li>DankPyon.Medieval.Overhaul</li>
    </loadAfter>
</ModMetaData>
